<?xml version="1.0" encoding="UTF-8" standalone="yes"?><p:sldLayout xmlns:a="http://schemas.openxmlformats.org/drawingml/2006/main" xmlns:r="http://schemas.openxmlformats.org/officeDocument/2006/relationships" xmlns:mc="http://schemas.openxmlformats.org/markup-compatibility/2006" xmlns:mv="urn:schemas-microsoft-com:mac:vml" xmlns:p="http://schemas.openxmlformats.org/presentationml/2006/main" xmlns:c="http://schemas.openxmlformats.org/drawingml/2006/chart" xmlns:dgm="http://schemas.openxmlformats.org/drawingml/2006/diagram" xmlns:o="urn:schemas-microsoft-com:office:office" xmlns:v="urn:schemas-microsoft-com:vml" xmlns:pvml="urn:schemas-microsoft-com:office:powerpoint" xmlns:com="http://schemas.openxmlformats.org/drawingml/2006/compatibility" xmlns:p14="http://schemas.microsoft.com/office/powerpoint/2010/main" type="title"><p:cSld name="Title Slide"><p:spTree><p:nvGrpSpPr><p:cNvPr id="48" name="Shape 48"/><p:cNvGrpSpPr/><p:nvPr/></p:nvGrpSpPr><p:grpSpPr><a:xfrm><a:off x="0" y="0"/><a:ext cx="0" cy="0"/><a:chOff x="0" y="0"/><a:chExt cx="0" cy="0"/></a:xfrm></p:grpSpPr><p:sp><p:nvSpPr><p:cNvPr id="49" name="Shape 49"/><p:cNvSpPr/><p:nvPr/></p:nvSpPr><p:spPr><a:xfrm><a:off x="0" y="0"/><a:ext cx="9144000" cy="3723299"/></a:xfrm><a:prstGeom prst="rect"><a:avLst/></a:prstGeom><a:solidFill><a:srgbClr val="000000"/></a:solidFill><a:ln><a:noFill/></a:ln></p:spPr><p:txBody><a:bodyPr anchorCtr="0" anchor="ctr" bIns="45700" lIns="91425" rIns="91425" tIns="45700"><a:noAutofit/></a:bodyPr><a:lstStyle/><a:p><a:pPr><a:spcBef><a:spcPts val="0"/></a:spcBef><a:buNone/></a:pPr><a:r><a:t></a:t></a:r><a:endParaRPr/></a:p></p:txBody></p:sp><p:sp><p:nvSpPr><p:cNvPr id="50" name="Shape 50"/><p:cNvSpPr txBox="1"/><p:nvPr><p:ph type="ctrTitle"/></p:nvPr></p:nvSpPr><p:spPr><a:xfrm><a:off x="391160" y="1433988"/><a:ext cx="8351399" cy="421499"/></a:xfrm><a:prstGeom prst="rect"><a:avLst/></a:prstGeom></p:spPr><p:txBody><a:bodyPr anchorCtr="0" anchor="ctr" bIns="91425" lIns="91425" rIns="91425" tIns="91425"/><a:lstStyle><a:lvl1pPr><a:spcBef><a:spcPts val="0"/></a:spcBef><a:buClr><a:schemeClr val="lt1"/></a:buClr><a:buSzPct val="100000"/><a:buFont typeface="Tahoma"/><a:defRPr sz="3600"><a:solidFill><a:schemeClr val="lt1"/></a:solidFill><a:latin typeface="Tahoma"/><a:ea typeface="Tahoma"/><a:cs typeface="Tahoma"/><a:sym typeface="Tahoma"/></a:defRPr></a:lvl1pPr><a:lvl2pPr><a:spcBef><a:spcPts val="0"/></a:spcBef><a:buClr><a:schemeClr val="lt1"/></a:buClr><a:buSzPct val="100000"/><a:buFont typeface="Tahoma"/><a:defRPr sz="3600"><a:solidFill><a:schemeClr val="lt1"/></a:solidFill><a:latin typeface="Tahoma"/><a:ea typeface="Tahoma"/><a:cs typeface="Tahoma"/><a:sym typeface="Tahoma"/></a:defRPr></a:lvl2pPr><a:lvl3pPr><a:spcBef><a:spcPts val="0"/></a:spcBef><a:buClr><a:schemeClr val="lt1"/></a:buClr><a:buSzPct val="100000"/><a:buFont typeface="Tahoma"/><a:defRPr sz="3600"><a:solidFill><a:schemeClr val="lt1"/></a:solidFill><a:latin typeface="Tahoma"/><a:ea typeface="Tahoma"/><a:cs typeface="Tahoma"/><a:sym typeface="Tahoma"/></a:defRPr></a:lvl3pPr><a:lvl4pPr><a:spcBef><a:spcPts val="0"/></a:spcBef><a:buClr><a:schemeClr val="lt1"/></a:buClr><a:buSzPct val="100000"/><a:buFont typeface="Tahoma"/><a:defRPr sz="3600"><a:solidFill><a:schemeClr val="lt1"/></a:solidFill><a:latin typeface="Tahoma"/><a:ea typeface="Tahoma"/><a:cs typeface="Tahoma"/><a:sym typeface="Tahoma"/></a:defRPr></a:lvl4pPr><a:lvl5pPr><a:spcBef><a:spcPts val="0"/></a:spcBef><a:buClr><a:schemeClr val="lt1"/></a:buClr><a:buSzPct val="100000"/><a:buFont typeface="Tahoma"/><a:defRPr sz="3600"><a:solidFill><a:schemeClr val="lt1"/></a:solidFill><a:latin typeface="Tahoma"/><a:ea typeface="Tahoma"/><a:cs typeface="Tahoma"/><a:sym typeface="Tahoma"/></a:defRPr></a:lvl5pPr><a:lvl6pPr><a:spcBef><a:spcPts val="0"/></a:spcBef><a:buClr><a:schemeClr val="lt1"/></a:buClr><a:buSzPct val="100000"/><a:buFont typeface="Tahoma"/><a:defRPr sz="3600"><a:solidFill><a:schemeClr val="lt1"/></a:solidFill><a:latin typeface="Tahoma"/><a:ea typeface="Tahoma"/><a:cs typeface="Tahoma"/><a:sym typeface="Tahoma"/></a:defRPr></a:lvl6pPr><a:lvl7pPr><a:spcBef><a:spcPts val="0"/></a:spcBef><a:buClr><a:schemeClr val="lt1"/></a:buClr><a:buSzPct val="100000"/><a:buFont typeface="Tahoma"/><a:defRPr sz="3600"><a:solidFill><a:schemeClr val="lt1"/></a:solidFill><a:latin typeface="Tahoma"/><a:ea typeface="Tahoma"/><a:cs typeface="Tahoma"/><a:sym typeface="Tahoma"/></a:defRPr></a:lvl7pPr><a:lvl8pPr><a:spcBef><a:spcPts val="0"/></a:spcBef><a:buClr><a:schemeClr val="lt1"/></a:buClr><a:buSzPct val="100000"/><a:buFont typeface="Tahoma"/><a:defRPr sz="3600"><a:solidFill><a:schemeClr val="lt1"/></a:solidFill><a:latin typeface="Tahoma"/><a:ea typeface="Tahoma"/><a:cs typeface="Tahoma"/><a:sym typeface="Tahoma"/></a:defRPr></a:lvl8pPr><a:lvl9pPr><a:spcBef><a:spcPts val="0"/></a:spcBef><a:buClr><a:schemeClr val="lt1"/></a:buClr><a:buSzPct val="100000"/><a:buFont typeface="Tahoma"/><a:defRPr sz="3600"><a:solidFill><a:schemeClr val="lt1"/></a:solidFill><a:latin typeface="Tahoma"/><a:ea typeface="Tahoma"/><a:cs typeface="Tahoma"/><a:sym typeface="Tahoma"/></a:defRPr></a:lvl9pPr></a:lstStyle><a:p/></p:txBody></p:sp><p:sp><p:nvSpPr><p:cNvPr id="51" name="Shape 51"/><p:cNvSpPr txBox="1"/><p:nvPr><p:ph idx="1" type="subTitle"/></p:nvPr></p:nvSpPr><p:spPr><a:xfrm><a:off x="403761" y="1982435"/><a:ext cx="8342400" cy="342300"/></a:xfrm><a:prstGeom prst="rect"><a:avLst/></a:prstGeom></p:spPr><p:txBody><a:bodyPr anchorCtr="0" anchor="ctr" bIns="91425" lIns="91425" rIns="91425" tIns="91425"/><a:lstStyle><a:lvl1pPr algn="ctr"><a:spcBef><a:spcPts val="0"/></a:spcBef><a:buClr><a:schemeClr val="lt1"/></a:buClr><a:buSzPct val="100000"/><a:buFont typeface="Times New Roman"/><a:buNone/><a:defRPr i="1" sz="2400"><a:solidFill><a:schemeClr val="lt1"/></a:solidFill><a:latin typeface="Times New Roman"/><a:ea typeface="Times New Roman"/><a:cs typeface="Times New Roman"/><a:sym typeface="Times New Roman"/></a:defRPr></a:lvl1pPr><a:lvl2pPr algn="ctr"><a:spcBef><a:spcPts val="0"/></a:spcBef><a:buClr><a:schemeClr val="lt1"/></a:buClr><a:buSzPct val="100000"/><a:buFont typeface="Times New Roman"/><a:buNone/><a:defRPr i="1" sz="2400"><a:solidFill><a:schemeClr val="lt1"/></a:solidFill><a:latin typeface="Times New Roman"/><a:ea typeface="Times New Roman"/><a:cs typeface="Times New Roman"/><a:sym typeface="Times New Roman"/></a:defRPr></a:lvl2pPr><a:lvl3pPr algn="ctr"><a:spcBef><a:spcPts val="0"/></a:spcBef><a:buClr><a:schemeClr val="lt1"/></a:buClr><a:buSzPct val="100000"/><a:buFont typeface="Times New Roman"/><a:buNone/><a:defRPr i="1" sz="2400"><a:solidFill><a:schemeClr val="lt1"/></a:solidFill><a:latin typeface="Times New Roman"/><a:ea typeface="Times New Roman"/><a:cs typeface="Times New Roman"/><a:sym typeface="Times New Roman"/></a:defRPr></a:lvl3pPr><a:lvl4pPr algn="ctr"><a:spcBef><a:spcPts val="0"/></a:spcBef><a:buClr><a:schemeClr val="lt1"/></a:buClr><a:buSzPct val="100000"/><a:buFont typeface="Times New Roman"/><a:buNone/><a:defRPr i="1" sz="2400"><a:solidFill><a:schemeClr val="lt1"/></a:solidFill><a:latin typeface="Times New Roman"/><a:ea typeface="Times New Roman"/><a:cs typeface="Times New Roman"/><a:sym typeface="Times New Roman"/></a:defRPr></a:lvl4pPr><a:lvl5pPr algn="ctr"><a:spcBef><a:spcPts val="0"/></a:spcBef><a:buClr><a:schemeClr val="lt1"/></a:buClr><a:buSzPct val="100000"/><a:buFont typeface="Times New Roman"/><a:buNone/><a:defRPr i="1" sz="2400"><a:solidFill><a:schemeClr val="lt1"/></a:solidFill><a:latin typeface="Times New Roman"/><a:ea typeface="Times New Roman"/><a:cs typeface="Times New Roman"/><a:sym typeface="Times New Roman"/></a:defRPr></a:lvl5pPr><a:lvl6pPr algn="ctr"><a:spcBef><a:spcPts val="0"/></a:spcBef><a:buClr><a:schemeClr val="lt1"/></a:buClr><a:buSzPct val="100000"/><a:buFont typeface="Times New Roman"/><a:buNone/><a:defRPr i="1" sz="2400"><a:solidFill><a:schemeClr val="lt1"/></a:solidFill><a:latin typeface="Times New Roman"/><a:ea typeface="Times New Roman"/><a:cs typeface="Times New Roman"/><a:sym typeface="Times New Roman"/></a:defRPr></a:lvl6pPr><a:lvl7pPr algn="ctr"><a:spcBef><a:spcPts val="0"/></a:spcBef><a:buClr><a:schemeClr val="lt1"/></a:buClr><a:buSzPct val="100000"/><a:buFont typeface="Times New Roman"/><a:buNone/><a:defRPr i="1" sz="2400"><a:solidFill><a:schemeClr val="lt1"/></a:solidFill><a:latin typeface="Times New Roman"/><a:ea typeface="Times New Roman"/><a:cs typeface="Times New Roman"/><a:sym typeface="Times New Roman"/></a:defRPr></a:lvl7pPr><a:lvl8pPr algn="ctr"><a:spcBef><a:spcPts val="0"/></a:spcBef><a:buClr><a:schemeClr val="lt1"/></a:buClr><a:buSzPct val="100000"/><a:buFont typeface="Times New Roman"/><a:buNone/><a:defRPr i="1" sz="2400"><a:solidFill><a:schemeClr val="lt1"/></a:solidFill><a:latin typeface="Times New Roman"/><a:ea typeface="Times New Roman"/><a:cs typeface="Times New Roman"/><a:sym typeface="Times New Roman"/></a:defRPr></a:lvl8pPr><a:lvl9pPr algn="ctr"><a:spcBef><a:spcPts val="0"/></a:spcBef><a:buClr><a:schemeClr val="lt1"/></a:buClr><a:buSzPct val="100000"/><a:buFont typeface="Times New Roman"/><a:buNone/><a:defRPr i="1" sz="2400"><a:solidFill><a:schemeClr val="lt1"/></a:solidFill><a:latin typeface="Times New Roman"/><a:ea typeface="Times New Roman"/><a:cs typeface="Times New Roman"/><a:sym typeface="Times New Roman"/></a:defRPr></a:lvl9pPr></a:lstStyle><a:p/></p:txBody></p:sp><p:cxnSp><p:nvCxnSpPr><p:cNvPr id="52" name="Shape 52"/><p:cNvCxnSpPr/><p:nvPr/></p:nvCxnSpPr><p:spPr><a:xfrm><a:off x="2258800" y="1912668"/><a:ext cx="4621799" cy="10799"/></a:xfrm><a:prstGeom prst="straightConnector1"><a:avLst/></a:prstGeom><a:noFill/><a:ln cap="rnd" w="25400"><a:solidFill><a:schemeClr val="accent2"/></a:solidFill><a:prstDash val="dot"/><a:round/><a:headEnd len="med" w="med" type="none"/><a:tailEnd len="med" w="med" type="none"/></a:ln></p:spPr></p:cxnSp><p:sp><p:nvSpPr><p:cNvPr id="53" name="Shape 53"/><p:cNvSpPr/><p:nvPr/></p:nvSpPr><p:spPr><a:xfrm><a:off x="0" y="3030297"/><a:ext cx="9143999" cy="795916"/></a:xfrm><a:custGeom><a:pathLst><a:path extrusionOk="0" h="1440573" w="9144000"><a:moveTo><a:pt x="8881" y="1"/></a:moveTo><a:lnTo><a:pt x="9126239" y="44075"/></a:lnTo><a:lnTo><a:pt x="9144000" y="1303180"/></a:lnTo><a:lnTo><a:pt x="8922142" y="1440573"/></a:lnTo><a:lnTo><a:pt x="8672386" y="1291790"/></a:lnTo><a:lnTo><a:pt x="8449199" y="1414005"/></a:lnTo><a:lnTo><a:pt x="8210071" y="1302417"/></a:lnTo><a:lnTo><a:pt x="7976257" y="1408691"/></a:lnTo><a:lnTo><a:pt x="7737129" y="1286476"/></a:lnTo><a:lnTo><a:pt x="7503314" y="1414005"/></a:lnTo><a:lnTo><a:pt x="7269500" y="1291790"/></a:lnTo><a:lnTo><a:pt x="7030372" y="1414005"/></a:lnTo><a:lnTo><a:pt x="6796557" y="1281162"/></a:lnTo><a:lnTo><a:pt x="6568057" y="1414005"/></a:lnTo><a:lnTo><a:pt x="6334243" y="1281163"/></a:lnTo><a:lnTo><a:pt x="6100428" y="1419319"/></a:lnTo><a:lnTo><a:pt x="5866614" y="1281163"/></a:lnTo><a:lnTo><a:pt x="5632800" y="1424632"/></a:lnTo><a:lnTo><a:pt x="5388357" y="1286476"/></a:lnTo><a:lnTo><a:pt x="5154543" y="1424632"/></a:lnTo><a:lnTo><a:pt x="4920729" y="1297104"/></a:lnTo><a:lnTo><a:pt x="4686914" y="1429946"/></a:lnTo><a:lnTo><a:pt x="4447786" y="1291790"/></a:lnTo><a:lnTo><a:pt x="4219286" y="1435260"/></a:lnTo><a:lnTo><a:pt x="3980157" y="1281163"/></a:lnTo><a:lnTo><a:pt x="3746343" y="1429946"/></a:lnTo><a:lnTo><a:pt x="3512529" y="1291790"/></a:lnTo><a:lnTo><a:pt x="3284028" y="1429946"/></a:lnTo><a:lnTo><a:pt x="3044900" y="1297104"/></a:lnTo><a:lnTo><a:pt x="2805772" y="1429946"/></a:lnTo><a:lnTo><a:pt x="2571958" y="1297104"/></a:lnTo><a:lnTo><a:pt x="2343457" y="1429946"/></a:lnTo><a:lnTo><a:pt x="2104329" y="1291790"/></a:lnTo><a:lnTo><a:pt x="1865201" y="1435260"/></a:lnTo><a:lnTo><a:pt x="1631386" y="1281163"/></a:lnTo><a:lnTo><a:pt x="1402886" y="1435260"/></a:lnTo><a:lnTo><a:pt x="1163758" y="1291790"/></a:lnTo><a:lnTo><a:pt x="935257" y="1435260"/></a:lnTo><a:lnTo><a:pt x="696129" y="1291790"/></a:lnTo><a:lnTo><a:pt x="457001" y="1429946"/></a:lnTo><a:lnTo><a:pt x="217872" y="1291790"/></a:lnTo><a:lnTo><a:pt x="0" y="1435260"/></a:lnTo><a:cubicBezTo><a:pt x="2960" y="956840"/><a:pt x="5921" y="478421"/><a:pt x="8881" y="1"/></a:cubicBezTo><a:close/></a:path></a:pathLst></a:custGeom><a:solidFill><a:schemeClr val="dk2"/></a:solidFill><a:ln><a:noFill/></a:ln></p:spPr><p:txBody><a:bodyPr anchorCtr="0" anchor="ctr" bIns="45700" lIns="91425" rIns="91425" tIns="45700"><a:noAutofit/></a:bodyPr><a:lstStyle/><a:p><a:pPr><a:spcBef><a:spcPts val="0"/></a:spcBef><a:buNone/></a:pPr><a:r><a:t></a:t></a:r><a:endParaRPr/></a:p></p:txBody></p:sp><p:sp><p:nvSpPr><p:cNvPr id="54" name="Shape 54"/><p:cNvSpPr txBox="1"/><p:nvPr><p:ph idx="12" type="sldNum"/></p:nvPr></p:nvSpPr><p:spPr><a:xfrm><a:off x="8556791" y="4749850"/><a:ext cx="548699" cy="393600"/></a:xfrm><a:prstGeom prst="rect"><a:avLst/></a:prstGeom></p:spPr><p:txBody><a:bodyPr anchorCtr="0" anchor="ctr" bIns="91425" lIns="91425" rIns="91425" tIns="91425"><a:noAutofit/></a:bodyPr><a:lstStyle><a:lvl1pPr><a:spcBef><a:spcPts val="0"/></a:spcBef><a:buNone/><a:defRPr/></a:lvl1pPr></a:lstStyle><a:p><a:pPr><a:spcBef><a:spcPts val="0"/></a:spcBef><a:buNone/></a:pPr><a:fld id="{00000000-1234-1234-1234-123412341234}" type="slidenum"><a:rPr lang="en-GB"/><a:t>‹#›</a:t></a:fld></a:p></p:txBody></p:sp></p:spTree></p:cSld><p:clrMapOvr><a:masterClrMapping/></p:clrMapOvr></p:sldLayout>